mortar_rdb/__init__.py
mortar_rdb/compat.py
mortar_rdb/controlled.py
mortar_rdb/interfaces.py
mortar_rdb/testing.py
mortar_rdb/sequence/__init__.py
mortar_rdb/sequence/generic.py
mortar_rdb/tests/__init__.py
mortar_rdb/tests/base.py
mortar_rdb/tests/test_controlled_schema.py
mortar_rdb/tests/test_datetime.py
mortar_rdb/tests/test_declarative_base.py
mortar_rdb/tests/test_register_session.py
mortar_rdb/tests/test_scripts.py
mortar_rdb/tests/test_testing.py
mortar_rdb/tests/test_utility.py
mortar_rdb-3.0.0.dist-info/METADATA
mortar_rdb-3.0.0.dist-info/WHEEL
mortar_rdb-3.0.0.dist-info/top_level.txt
mortar_rdb-3.0.0.dist-info/RECORD
